riscflow/version.py
riscflow-0.0.3.dist-info/METADATA
riscflow-0.0.3.dist-info/WHEEL
riscflow-0.0.3.dist-info/top_level.txt
riscflow-0.0.3.dist-info/RECORD
