Metadata-Version: 2.1
Name: riscflow
Version: 0.0.3
Summary: A library for control flow graph analysis of RISC-V assembly
Author: Akshit Sharma
Author-email: akshitsharma@mines.edu
